{
    "openapi": "3.0.0",
    "info": {
        "title": "Orthoplex Multi-Tenant SaaS API",
        "description": "Comprehensive multi-tenant SaaS backend with hybrid authentication, RBAC, and analytics. Built with Laravel, Stancl Tenancy, and JWT authentication.",
        "contact": {
            "name": "Orthoplex Support Team",
            "email": "support@orthoplex.com"
        },
        "license": {
            "name": "MIT License",
            "url": "https://opensource.org/licenses/MIT"
        },
        "version": "1.0.0"
    },
    "paths": {
        "/api/register": {
            "post": {
                "tags": [
                    "Authentication"
                ],
                "summary": "Register a new user",
                "description": "Register a new user account with email verification",
                "operationId": "registerUser",
                "requestBody": {
                    "description": "User registration data",
                    "required": true,
                    "content": {
                        "application/json": {
                            "schema": {
                                "required": [
                                    "name",
                                    "email",
                                    "password",
                                    "password_confirmation"
                                ],
                                "properties": {
                                    "name": {
                                        "description": "User full name",
                                        "type": "string",
                                        "example": "John Doe"
                                    },
                                    "email": {
                                        "description": "User email address",
                                        "type": "string",
                                        "format": "email",
                                        "example": "john@example.com"
                                    },
                                    "password": {
                                        "description": "User password (min 8 chars)",
                                        "type": "string",
                                        "format": "password",
                                        "example": "password123"
                                    },
                                    "password_confirmation": {
                                        "description": "Password confirmation",
                                        "type": "string",
                                        "format": "password",
                                        "example": "password123"
                                    }
                                },
                                "type": "object"
                            }
                        }
                    }
                },
                "responses": {
                    "201": {
                        "description": "User registered successfully",
                        "content": {
                            "application/json": {
                                "schema": {
                                    "allOf": [
                                        {
                                            "$ref": "#/components/schemas/ApiResponse"
                                        },
                                        {
                                            "properties": {
                                                "data": {
                                                    "properties": {
                                                        "user": {
                                                            "$ref": "#/components/schemas/UserProfile"
                                                        },
                                                        "verification_sent": {
                                                            "type": "boolean",
                                                            "example": true
                                                        }
                                                    },
                                                    "type": "object"
                                                }
                                            },
                                            "type": "object"
                                        }
                                    ]
                                }
                            }
                        }
                    },
                    "400": {
                        "description": "Registration error",
                        "content": {
                            "application/json": {
                                "schema": {
                                    "$ref": "#/components/schemas/ErrorResponse"
                                }
                            }
                        }
                    },
                    "422": {
                        "description": "Validation error",
                        "content": {
                            "application/json": {
                                "schema": {
                                    "$ref": "#/components/schemas/ErrorResponse"
                                }
                            }
                        }
                    }
                }
            }
        },
        "/api/auth/login": {
            "post": {
                "tags": [
                    "Authentication"
                ],
                "summary": "Authenticate user",
                "description": "Authenticate user with email and password, supports 2FA",
                "operationId": "loginUser",
                "requestBody": {
                    "description": "User login credentials",
                    "required": true,
                    "content": {
                        "application/json": {
                            "schema": {
                                "required": [
                                    "email",
                                    "password"
                                ],
                                "properties": {
                                    "email": {
                                        "description": "User email address",
                                        "type": "string",
                                        "format": "email",
                                        "example": "john@example.com"
                                    },
                                    "password": {
                                        "description": "User password",
                                        "type": "string",
                                        "format": "password",
                                        "example": "password123"
                                    },
                                    "remember_me": {
                                        "description": "Remember user session",
                                        "type": "boolean",
                                        "example": false
                                    }
                                },
                                "type": "object"
                            }
                        }
                    }
                },
                "responses": {
                    "200": {
                        "description": "Authentication successful",
                        "content": {
                            "application/json": {
                                "schema": {
                                    "allOf": [
                                        {
                                            "$ref": "#/components/schemas/ApiResponse"
                                        },
                                        {
                                            "properties": {
                                                "data": {
                                                    "$ref": "#/components/schemas/AuthToken"
                                                }
                                            },
                                            "type": "object"
                                        }
                                    ]
                                }
                            }
                        }
                    },
                    "202": {
                        "description": "2FA verification required",
                        "content": {
                            "application/json": {
                                "schema": {
                                    "allOf": [
                                        {
                                            "$ref": "#/components/schemas/ApiResponse"
                                        },
                                        {
                                            "properties": {
                                                "data": {
                                                    "$ref": "#/components/schemas/TwoFactorRequired"
                                                }
                                            },
                                            "type": "object"
                                        }
                                    ]
                                }
                            }
                        }
                    },
                    "401": {
                        "description": "Invalid credentials",
                        "content": {
                            "application/json": {
                                "schema": {
                                    "$ref": "#/components/schemas/ErrorResponse"
                                }
                            }
                        }
                    },
                    "403": {
                        "description": "Account not verified, suspended, or inactive",
                        "content": {
                            "application/json": {
                                "schema": {
                                    "$ref": "#/components/schemas/ErrorResponse"
                                }
                            }
                        }
                    },
                    "422": {
                        "description": "Validation error",
                        "content": {
                            "application/json": {
                                "schema": {
                                    "$ref": "#/components/schemas/ErrorResponse"
                                }
                            }
                        }
                    }
                }
            }
        },
        "/api/auth/login/2fa": {
            "post": {
                "tags": [
                    "Authentication"
                ],
                "summary": "Verify 2FA code",
                "description": "Complete login process by verifying 2FA code",
                "operationId": "verifyTwoFactor",
                "requestBody": {
                    "description": "2FA verification data",
                    "required": true,
                    "content": {
                        "application/json": {
                            "schema": {
                                "required": [
                                    "user_id",
                                    "otp"
                                ],
                                "properties": {
                                    "user_id": {
                                        "description": "User ID from login response",
                                        "type": "integer",
                                        "example": 1
                                    },
                                    "otp": {
                                        "description": "6-digit 2FA code",
                                        "type": "string",
                                        "example": "123456"
                                    }
                                },
                                "type": "object"
                            }
                        }
                    }
                },
                "responses": {
                    "200": {
                        "description": "2FA verification successful",
                        "content": {
                            "application/json": {
                                "schema": {
                                    "allOf": [
                                        {
                                            "$ref": "#/components/schemas/ApiResponse"
                                        },
                                        {
                                            "properties": {
                                                "data": {
                                                    "$ref": "#/components/schemas/AuthToken"
                                                }
                                            },
                                            "type": "object"
                                        }
                                    ]
                                }
                            }
                        }
                    },
                    "401": {
                        "description": "Invalid 2FA code",
                        "content": {
                            "application/json": {
                                "schema": {
                                    "$ref": "#/components/schemas/ErrorResponse"
                                }
                            }
                        }
                    },
                    "422": {
                        "description": "Validation error",
                        "content": {
                            "application/json": {
                                "schema": {
                                    "$ref": "#/components/schemas/ErrorResponse"
                                }
                            }
                        }
                    }
                }
            }
        },
        "/api/auth/email/verify": {
            "get": {
                "tags": [
                    "Authentication"
                ],
                "summary": "Verify email address",
                "description": "Verify user's email address using magic link token",
                "operationId": "verifyEmail",
                "parameters": [
                    {
                        "name": "token",
                        "in": "query",
                        "description": "Email verification token from magic link",
                        "required": true,
                        "schema": {
                            "type": "string"
                        }
                    }
                ],
                "responses": {
                    "200": {
                        "description": "Email verified successfully",
                        "content": {
                            "application/json": {
                                "schema": {
                                    "allOf": [
                                        {
                                            "$ref": "#/components/schemas/ApiResponse"
                                        },
                                        {
                                            "properties": {
                                                "data": {
                                                    "type": "null"
                                                }
                                            },
                                            "type": "object"
                                        }
                                    ]
                                }
                            }
                        }
                    },
                    "400": {
                        "description": "Invalid or expired verification token",
                        "content": {
                            "application/json": {
                                "schema": {
                                    "$ref": "#/components/schemas/ErrorResponse"
                                }
                            }
                        }
                    },
                    "404": {
                        "description": "User not found",
                        "content": {
                            "application/json": {
                                "schema": {
                                    "$ref": "#/components/schemas/ErrorResponse"
                                }
                            }
                        }
                    }
                }
            }
        },
        "/api/auth/email/resend": {
            "post": {
                "tags": [
                    "Authentication"
                ],
                "summary": "Resend email verification",
                "description": "Resend email verification link to user",
                "operationId": "resendVerification",
                "requestBody": {
                    "description": "Email to resend verification to",
                    "required": true,
                    "content": {
                        "application/json": {
                            "schema": {
                                "required": [
                                    "email"
                                ],
                                "properties": {
                                    "email": {
                                        "description": "User email address",
                                        "type": "string",
                                        "format": "email",
                                        "example": "john@example.com"
                                    }
                                },
                                "type": "object"
                            }
                        }
                    }
                },
                "responses": {
                    "200": {
                        "description": "Verification link sent",
                        "content": {
                            "application/json": {
                                "schema": {
                                    "allOf": [
                                        {
                                            "$ref": "#/components/schemas/ApiResponse"
                                        },
                                        {
                                            "properties": {
                                                "data": {
                                                    "type": "null"
                                                }
                                            },
                                            "type": "object"
                                        }
                                    ]
                                }
                            }
                        }
                    },
                    "400": {
                        "description": "Email already verified or resend failed",
                        "content": {
                            "application/json": {
                                "schema": {
                                    "$ref": "#/components/schemas/ErrorResponse"
                                }
                            }
                        }
                    },
                    "404": {
                        "description": "User not found",
                        "content": {
                            "application/json": {
                                "schema": {
                                    "$ref": "#/components/schemas/ErrorResponse"
                                }
                            }
                        }
                    },
                    "422": {
                        "description": "Validation error",
                        "content": {
                            "application/json": {
                                "schema": {
                                    "$ref": "#/components/schemas/ErrorResponse"
                                }
                            }
                        }
                    }
                }
            }
        },
        "/api/v1/users": {
            "get": {
                "tags": [
                    "Users"
                ],
                "summary": "Get list of users",
                "description": "Retrieve a paginated list of users with optional filtering, sorting, and includes",
                "operationId": "getUsersList",
                "parameters": [
                    {
                        "name": "filter[name]",
                        "in": "query",
                        "description": "Filter by user name",
                        "required": false,
                        "schema": {
                            "type": "string"
                        }
                    },
                    {
                        "name": "filter[email]",
                        "in": "query",
                        "description": "Filter by user email",
                        "required": false,
                        "schema": {
                            "type": "string"
                        }
                    },
                    {
                        "name": "filter[status]",
                        "in": "query",
                        "description": "Filter by user status",
                        "required": false,
                        "schema": {
                            "type": "string",
                            "enum": [
                                "active",
                                "inactive",
                                "suspended"
                            ]
                        }
                    },
                    {
                        "name": "sort",
                        "in": "query",
                        "description": "Sort by field (name, email, created_at)",
                        "required": false,
                        "schema": {
                            "type": "string"
                        }
                    },
                    {
                        "name": "include",
                        "in": "query",
                        "description": "Include relations (roles)",
                        "required": false,
                        "schema": {
                            "type": "string"
                        }
                    },
                    {
                        "name": "cursor",
                        "in": "query",
                        "description": "Cursor for pagination",
                        "required": false,
                        "schema": {
                            "type": "string"
                        }
                    }
                ],
                "responses": {
                    "200": {
                        "description": "Users retrieved successfully",
                        "content": {
                            "application/json": {
                                "schema": {
                                    "allOf": [
                                        {
                                            "$ref": "#/components/schemas/ApiResponse"
                                        },
                                        {
                                            "properties": {
                                                "data": {
                                                    "$ref": "#/components/schemas/UserPagination"
                                                }
                                            },
                                            "type": "object"
                                        }
                                    ]
                                }
                            }
                        }
                    },
                    "401": {
                        "description": "Unauthorized",
                        "content": {
                            "application/json": {
                                "schema": {
                                    "$ref": "#/components/schemas/ErrorResponse"
                                }
                            }
                        }
                    },
                    "403": {
                        "description": "Forbidden - Insufficient permissions",
                        "content": {
                            "application/json": {
                                "schema": {
                                    "$ref": "#/components/schemas/ErrorResponse"
                                }
                            }
                        }
                    }
                },
                "security": [
                    {
                        "bearerAuth": []
                    }
                ]
            },
            "post": {
                "tags": [
                    "Users"
                ],
                "summary": "Create a new user",
                "description": "Create a new user in the current tenant",
                "operationId": "createUser",
                "requestBody": {
                    "description": "User data",
                    "required": true,
                    "content": {
                        "application/json": {
                            "schema": {
                                "required": [
                                    "name",
                                    "email",
                                    "password"
                                ],
                                "properties": {
                                    "name": {
                                        "description": "User full name",
                                        "type": "string",
                                        "example": "John Doe"
                                    },
                                    "email": {
                                        "description": "User email address",
                                        "type": "string",
                                        "format": "email",
                                        "example": "john@example.com"
                                    },
                                    "password": {
                                        "description": "User password (min 8 chars)",
                                        "type": "string",
                                        "format": "password",
                                        "example": "password123"
                                    },
                                    "status": {
                                        "description": "User status",
                                        "type": "string",
                                        "enum": [
                                            "active",
                                            "inactive",
                                            "suspended"
                                        ],
                                        "example": "active"
                                    }
                                },
                                "type": "object"
                            }
                        }
                    }
                },
                "responses": {
                    "201": {
                        "description": "User created successfully",
                        "content": {
                            "application/json": {
                                "schema": {
                                    "allOf": [
                                        {
                                            "$ref": "#/components/schemas/ApiResponse"
                                        },
                                        {
                                            "properties": {
                                                "data": {
                                                    "$ref": "#/components/schemas/User"
                                                }
                                            },
                                            "type": "object"
                                        }
                                    ]
                                }
                            }
                        }
                    },
                    "422": {
                        "description": "Validation error",
                        "content": {
                            "application/json": {
                                "schema": {
                                    "$ref": "#/components/schemas/ErrorResponse"
                                }
                            }
                        }
                    },
                    "401": {
                        "description": "Unauthorized",
                        "content": {
                            "application/json": {
                                "schema": {
                                    "$ref": "#/components/schemas/ErrorResponse"
                                }
                            }
                        }
                    },
                    "403": {
                        "description": "Forbidden - Insufficient permissions",
                        "content": {
                            "application/json": {
                                "schema": {
                                    "$ref": "#/components/schemas/ErrorResponse"
                                }
                            }
                        }
                    }
                },
                "security": [
                    {
                        "bearerAuth": []
                    }
                ]
            }
        },
        "/api/v1/users/{id}": {
            "get": {
                "tags": [
                    "Users"
                ],
                "summary": "Get user by ID",
                "description": "Retrieve a specific user by their ID including roles",
                "operationId": "getUserById",
                "parameters": [
                    {
                        "name": "id",
                        "in": "path",
                        "description": "User ID",
                        "required": true,
                        "schema": {
                            "type": "integer"
                        }
                    }
                ],
                "responses": {
                    "200": {
                        "description": "User retrieved successfully",
                        "content": {
                            "application/json": {
                                "schema": {
                                    "allOf": [
                                        {
                                            "$ref": "#/components/schemas/ApiResponse"
                                        },
                                        {
                                            "properties": {
                                                "data": {
                                                    "$ref": "#/components/schemas/User"
                                                }
                                            },
                                            "type": "object"
                                        }
                                    ]
                                }
                            }
                        }
                    },
                    "404": {
                        "description": "User not found",
                        "content": {
                            "application/json": {
                                "schema": {
                                    "$ref": "#/components/schemas/ErrorResponse"
                                }
                            }
                        }
                    },
                    "401": {
                        "description": "Unauthorized",
                        "content": {
                            "application/json": {
                                "schema": {
                                    "$ref": "#/components/schemas/ErrorResponse"
                                }
                            }
                        }
                    },
                    "403": {
                        "description": "Forbidden - Insufficient permissions",
                        "content": {
                            "application/json": {
                                "schema": {
                                    "$ref": "#/components/schemas/ErrorResponse"
                                }
                            }
                        }
                    }
                },
                "security": [
                    {
                        "bearerAuth": []
                    }
                ]
            },
            "put": {
                "tags": [
                    "Users"
                ],
                "summary": "Update user",
                "description": "Update an existing user's information",
                "operationId": "updateUser",
                "parameters": [
                    {
                        "name": "id",
                        "in": "path",
                        "description": "User ID",
                        "required": true,
                        "schema": {
                            "type": "integer"
                        }
                    }
                ],
                "requestBody": {
                    "description": "User data to update",
                    "required": true,
                    "content": {
                        "application/json": {
                            "schema": {
                                "properties": {
                                    "name": {
                                        "description": "User full name",
                                        "type": "string",
                                        "example": "Jane Doe"
                                    },
                                    "email": {
                                        "description": "User email address",
                                        "type": "string",
                                        "format": "email",
                                        "example": "jane@example.com"
                                    },
                                    "password": {
                                        "description": "New password (min 8 chars)",
                                        "type": "string",
                                        "format": "password",
                                        "example": "newpassword123"
                                    },
                                    "status": {
                                        "description": "User status",
                                        "type": "string",
                                        "enum": [
                                            "active",
                                            "inactive",
                                            "suspended"
                                        ],
                                        "example": "active"
                                    },
                                    "email_verified_at": {
                                        "description": "Email verification timestamp",
                                        "type": "string",
                                        "format": "date-time"
                                    }
                                },
                                "type": "object"
                            }
                        }
                    }
                },
                "responses": {
                    "200": {
                        "description": "User updated successfully",
                        "content": {
                            "application/json": {
                                "schema": {
                                    "allOf": [
                                        {
                                            "$ref": "#/components/schemas/ApiResponse"
                                        },
                                        {
                                            "properties": {
                                                "data": {
                                                    "$ref": "#/components/schemas/User"
                                                }
                                            },
                                            "type": "object"
                                        }
                                    ]
                                }
                            }
                        }
                    },
                    "404": {
                        "description": "User not found",
                        "content": {
                            "application/json": {
                                "schema": {
                                    "$ref": "#/components/schemas/ErrorResponse"
                                }
                            }
                        }
                    },
                    "422": {
                        "description": "Validation error",
                        "content": {
                            "application/json": {
                                "schema": {
                                    "$ref": "#/components/schemas/ErrorResponse"
                                }
                            }
                        }
                    },
                    "401": {
                        "description": "Unauthorized",
                        "content": {
                            "application/json": {
                                "schema": {
                                    "$ref": "#/components/schemas/ErrorResponse"
                                }
                            }
                        }
                    },
                    "403": {
                        "description": "Forbidden - Insufficient permissions",
                        "content": {
                            "application/json": {
                                "schema": {
                                    "$ref": "#/components/schemas/ErrorResponse"
                                }
                            }
                        }
                    }
                },
                "security": [
                    {
                        "bearerAuth": []
                    }
                ]
            },
            "delete": {
                "tags": [
                    "Users"
                ],
                "summary": "Delete user",
                "description": "Soft delete a user (can be restored later)",
                "operationId": "deleteUser",
                "parameters": [
                    {
                        "name": "id",
                        "in": "path",
                        "description": "User ID to delete",
                        "required": true,
                        "schema": {
                            "type": "integer"
                        }
                    }
                ],
                "responses": {
                    "200": {
                        "description": "User deleted successfully",
                        "content": {
                            "application/json": {
                                "schema": {
                                    "allOf": [
                                        {
                                            "$ref": "#/components/schemas/ApiResponse"
                                        },
                                        {
                                            "properties": {
                                                "data": {
                                                    "type": "null"
                                                }
                                            },
                                            "type": "object"
                                        }
                                    ]
                                }
                            }
                        }
                    },
                    "404": {
                        "description": "User not found",
                        "content": {
                            "application/json": {
                                "schema": {
                                    "$ref": "#/components/schemas/ErrorResponse"
                                }
                            }
                        }
                    },
                    "422": {
                        "description": "Unable to delete user",
                        "content": {
                            "application/json": {
                                "schema": {
                                    "$ref": "#/components/schemas/ErrorResponse"
                                }
                            }
                        }
                    },
                    "401": {
                        "description": "Unauthorized",
                        "content": {
                            "application/json": {
                                "schema": {
                                    "$ref": "#/components/schemas/ErrorResponse"
                                }
                            }
                        }
                    },
                    "403": {
                        "description": "Forbidden - Insufficient permissions",
                        "content": {
                            "application/json": {
                                "schema": {
                                    "$ref": "#/components/schemas/ErrorResponse"
                                }
                            }
                        }
                    }
                },
                "security": [
                    {
                        "bearerAuth": []
                    }
                ]
            }
        },
        "/api/v1/users/bulk": {
            "post": {
                "tags": [
                    "Users"
                ],
                "summary": "Bulk user operations",
                "description": "Perform bulk operations on multiple users (delete, activate, deactivate, suspend)",
                "operationId": "bulkUserOperation",
                "requestBody": {
                    "description": "Bulk operation data",
                    "required": true,
                    "content": {
                        "application/json": {
                            "schema": {
                                "required": [
                                    "user_ids",
                                    "action"
                                ],
                                "properties": {
                                    "user_ids": {
                                        "description": "Array of user IDs",
                                        "type": "array",
                                        "items": {
                                            "type": "integer"
                                        },
                                        "example": [
                                            1,
                                            2,
                                            3
                                        ]
                                    },
                                    "action": {
                                        "description": "Bulk action to perform",
                                        "type": "string",
                                        "enum": [
                                            "delete",
                                            "activate",
                                            "deactivate",
                                            "suspend"
                                        ],
                                        "example": "activate"
                                    },
                                    "status": {
                                        "description": "New status for status change operations",
                                        "type": "string",
                                        "enum": [
                                            "active",
                                            "inactive",
                                            "suspended"
                                        ],
                                        "example": "active"
                                    }
                                },
                                "type": "object"
                            }
                        }
                    }
                },
                "responses": {
                    "200": {
                        "description": "Bulk operation completed",
                        "content": {
                            "application/json": {
                                "schema": {
                                    "allOf": [
                                        {
                                            "$ref": "#/components/schemas/ApiResponse"
                                        },
                                        {
                                            "properties": {
                                                "data": {
                                                    "description": "Results of bulk operation",
                                                    "type": "object",
                                                    "example": {
                                                        "1": true,
                                                        "2": true,
                                                        "3": false
                                                    }
                                                }
                                            },
                                            "type": "object"
                                        }
                                    ]
                                }
                            }
                        }
                    },
                    "422": {
                        "description": "Validation error",
                        "content": {
                            "application/json": {
                                "schema": {
                                    "$ref": "#/components/schemas/ErrorResponse"
                                }
                            }
                        }
                    },
                    "401": {
                        "description": "Unauthorized",
                        "content": {
                            "application/json": {
                                "schema": {
                                    "$ref": "#/components/schemas/ErrorResponse"
                                }
                            }
                        }
                    },
                    "403": {
                        "description": "Forbidden - Insufficient permissions",
                        "content": {
                            "application/json": {
                                "schema": {
                                    "$ref": "#/components/schemas/ErrorResponse"
                                }
                            }
                        }
                    }
                },
                "security": [
                    {
                        "bearerAuth": []
                    }
                ]
            }
        }
    },
    "components": {
        "schemas": {
            "AuthToken": {
                "properties": {
                    "access_token": {
                        "description": "JWT access token",
                        "type": "string"
                    },
                    "refresh_token": {
                        "description": "JWT refresh token",
                        "type": "string"
                    },
                    "token_type": {
                        "description": "Token type",
                        "type": "string",
                        "example": "bearer"
                    },
                    "expires_in": {
                        "description": "Token expiration time in seconds",
                        "type": "integer",
                        "example": 3600
                    }
                },
                "type": "object"
            },
            "UserProfile": {
                "properties": {
                    "id": {
                        "description": "User ID",
                        "type": "integer"
                    },
                    "global_id": {
                        "description": "Global user identifier",
                        "type": "string",
                        "format": "uuid"
                    },
                    "name": {
                        "description": "User full name",
                        "type": "string"
                    },
                    "email": {
                        "description": "User email address",
                        "type": "string",
                        "format": "email"
                    },
                    "email_verified_at": {
                        "description": "Email verification timestamp",
                        "type": "string",
                        "format": "date-time",
                        "nullable": true
                    },
                    "two_factor_enabled": {
                        "description": "Whether 2FA is enabled",
                        "type": "boolean"
                    },
                    "status": {
                        "description": "User status",
                        "type": "string",
                        "enum": [
                            "active",
                            "inactive",
                            "suspended"
                        ]
                    },
                    "created_at": {
                        "description": "Account creation timestamp",
                        "type": "string",
                        "format": "date-time"
                    }
                },
                "type": "object"
            },
            "TwoFactorRequired": {
                "properties": {
                    "user_id": {
                        "description": "User ID requiring 2FA",
                        "type": "integer"
                    },
                    "email": {
                        "description": "User email",
                        "type": "string",
                        "format": "email"
                    },
                    "requires_2fa": {
                        "description": "Indicates 2FA verification is required",
                        "type": "boolean",
                        "example": true
                    }
                },
                "type": "object"
            },
            "User": {
                "required": [
                    "id",
                    "name",
                    "email",
                    "global_id",
                    "status"
                ],
                "properties": {
                    "id": {
                        "description": "User ID",
                        "type": "integer"
                    },
                    "name": {
                        "description": "User full name",
                        "type": "string"
                    },
                    "email": {
                        "description": "User email address",
                        "type": "string",
                        "format": "email"
                    },
                    "email_verified_at": {
                        "description": "Email verification timestamp",
                        "type": "string",
                        "format": "date-time",
                        "nullable": true
                    },
                    "status": {
                        "description": "User status",
                        "type": "string",
                        "enum": [
                            "active",
                            "inactive",
                            "suspended"
                        ]
                    },
                    "global_id": {
                        "description": "Global identifier for synced resources",
                        "type": "string",
                        "format": "uuid"
                    },
                    "created_at": {
                        "description": "Creation timestamp",
                        "type": "string",
                        "format": "date-time"
                    },
                    "updated_at": {
                        "description": "Last update timestamp",
                        "type": "string",
                        "format": "date-time"
                    },
                    "deleted_at": {
                        "description": "Soft deletion timestamp",
                        "type": "string",
                        "format": "date-time",
                        "nullable": true
                    },
                    "roles": {
                        "description": "User roles",
                        "type": "array",
                        "items": {
                            "properties": {
                                "id": {
                                    "type": "integer"
                                },
                                "name": {
                                    "type": "string"
                                },
                                "guard_name": {
                                    "type": "string"
                                }
                            },
                            "type": "object"
                        }
                    }
                },
                "type": "object"
            },
            "UserPagination": {
                "properties": {
                    "data": {
                        "type": "array",
                        "items": {
                            "$ref": "#/components/schemas/User"
                        }
                    },
                    "path": {
                        "type": "string"
                    },
                    "per_page": {
                        "type": "integer"
                    },
                    "next_cursor": {
                        "type": "string",
                        "nullable": true
                    },
                    "prev_cursor": {
                        "type": "string",
                        "nullable": true
                    },
                    "next_page_url": {
                        "type": "string",
                        "nullable": true
                    },
                    "prev_page_url": {
                        "type": "string",
                        "nullable": true
                    }
                },
                "type": "object"
            },
            "ApiResponse": {
                "properties": {
                    "success": {
                        "description": "Request success status",
                        "type": "boolean"
                    },
                    "message": {
                        "description": "Response message",
                        "type": "string"
                    },
                    "data": {
                        "description": "Response data"
                    }
                },
                "type": "object"
            },
            "ErrorResponse": {
                "properties": {
                    "success": {
                        "type": "boolean",
                        "example": false
                    },
                    "message": {
                        "description": "Error message",
                        "type": "string"
                    },
                    "errors": {
                        "description": "Validation errors",
                        "type": "object"
                    }
                },
                "type": "object"
            }
        },
        "securitySchemes": {
            "bearerAuth": {
                "type": "http",
                "description": "JWT Authorization header using the Bearer scheme. Example: 'Bearer {token}'",
                "bearerFormat": "JWT",
                "scheme": "bearer"
            }
        }
    },
    "tags": [
        {
            "name": "Authentication",
            "description": "User authentication endpoints including login, registration, 2FA, and magic links"
        },
        {
            "name": "Users",
            "description": "User management operations including CRUD, role management, and bulk operations"
        }
    ]
}